setup.py
pywhois/__init__.py
pywhois/bin.py
pywhois.egg-info/PKG-INFO
pywhois.egg-info/SOURCES.txt
pywhois.egg-info/dependency_links.txt
pywhois.egg-info/entry_points.txt
pywhois.egg-info/not-zip-safe
pywhois.egg-info/top_level.txt